beancount_black/__init__.py
beancount_black/formatter.py
beancount_black/main.py
beancount_black-1.0.5.dist-info/LICENSE
beancount_black-1.0.5.dist-info/METADATA
beancount_black-1.0.5.dist-info/WHEEL
beancount_black-1.0.5.dist-info/entry_points.txt
beancount_black-1.0.5.dist-info/RECORD
