Metadata-Version: 2.1
Name: beancount-black
Version: 1.0.5
Summary: Opinioned beancount formatter library
Home-page: https://github.com/LaunchPlatform/beancount-black
License: MIT
Author: Fang-Pen Lin
Author-email: fangpen@launchplatform.com
Requires-Python: >=3.9,<4.0
Classifier: License :: OSI Approved :: MIT License
Classifier: Programming Language :: Python :: 3
Classifier: Programming Language :: Python :: 3.9
Classifier: Programming Language :: Python :: 3.10
Classifier: Programming Language :: Python :: 3.11
Requires-Dist: beancount-parser (>=1.0.1,<2.0.0)
Requires-Dist: click (>=7.0.0,<9.0.0)
Project-URL: Repository, https://github.com/LaunchPlatform/beancount-black
